[
  {
    "symbol": "FLEX",
    "entry_price": 148.0099945,
    "entry_date": 1780272000000,

    "current_price": 149.71001,
    "change_percent": 1.15,

    "days_held": 9,
    "price_group": "LARGE",

    "grade": "B",

    "score": 0,
    "breakout_strength": 0,
    "volume_ratio": 0,

    "resistance": 0,
    "touches": 0,
    "higher_lows": 0,

    "setup_type": "breakout",
    "insight": "Backtest watchlist stock"
  },

  {
    "symbol": "LOGI",
    "entry_price": 103.42,
    "entry_date": 1778025600000,

    "current_price": 110.81,
    "change_percent": 7.15,

    "days_held": 26,
    "price_group": "LARGE",

    "grade": "B",

    "score": 0,
    "breakout_strength": 0,
    "volume_ratio": 0,

    "resistance": 0,
    "touches": 0,
    "higher_lows": 0,

    "setup_type": "breakout",
    "insight": "Backtest watchlist stock"
  },

  {
    "symbol": "ROST",
    "entry_price": 234.67999,
    "entry_date": 1779753600000,

    "current_price": 240.13,
    "change_percent": 2.32,

    "days_held": 13,
    "price_group": "LARGE",

    "grade": "B",

    "score": 0,
    "breakout_strength": 0,
    "volume_ratio": 0,

    "resistance": 0,
    "touches": 0,
    "higher_lows": 0,

    "setup_type": "breakout",
    "insight": "Backtest watchlist stock"
  }
]
 